{

    "#":"Subscriber-specific parameters",

    "W2A_SUB_HOURS_TO_KEEP" : "120",
    "W2A_SUB_INTERVAL_SEC"  : "30",
    "W2A_SUB_BATCH_SIZE"    : "2000",

    
    "#":"Filter/Decoder-specific parameters",

    "W2A_FD_INTERVAL_SEC" : "30",
    "W2A_FD_START_MODE"   : "warm",
    "W2A_FD_DEBUG"        : "",

    
    "#":"APRS Publisher-specific parameters",

    "W2A_PUB_APRS_USER"         : "fakeUsr",
    "W2A_PUB_APRS_PASS"         : "fakePass",
    "W2A_PUB_APRS_INTERVAL_SEC" : "30",
    "W2A_PUB_APRS_START_MODE"   : "warm",
    "W2A_PUB_APRS_DEBUG"        : "debug",

    "#":"WSPR Publisher-specific parameters",

    "W2A_PUB_WSPR_INTERVAL_SEC" : "30",
    "W2A_PUB_WSPR_START_MODE"   : "warm",
    "W2A_PUB_WSPR_DEBUG"        : "debug"

}
